MANIFEST.in
README.md
setup.cfg
setup.py
backend/__init__.py
backend/apigen.py
backend/consul.py
backend/consumer.py
backend/decorator.py
backend/encoder.py
backend/entity.py
backend/exception.py
backend/logger.py
backend/response.py
backend/sender.py
backend/service_generator.py
backend/string_utils.py
backend/testgen.py
backend/validator.py
backend/validator_method.py
backend/visitor.py
templates/__init__.py
templates/api_add.txt
templates/api_all.txt
templates/api_base.txt
templates/api_delete.txt
templates/api_find.txt
templates/api_pagging.txt
templates/api_update.txt
templates/service_add.txt
templates/service_all.txt
templates/service_base.txt
templates/service_delete.txt
templates/service_find.txt
templates/service_pagging.txt
templates/service_update.txt
templates/test_api.txt
templates/test_base.txt
tests/__init__.py
tests/ast_model_visitor_test.py
tests/service_create_gen_test.py
tests/service_edit_gen_test.py
tests/validator_key_test.py
tests/validator_length_test.py
tests/validator_method_test.py
x_lib.egg-info/PKG-INFO
x_lib.egg-info/SOURCES.txt
x_lib.egg-info/dependency_links.txt
x_lib.egg-info/entry_points.txt
x_lib.egg-info/not-zip-safe
x_lib.egg-info/requires.txt
x_lib.egg-info/top_level.txt